kpandas/__init__.py
kpandas/df.py
kpandas-0.0.1.dist-info/WHEEL
kpandas-0.0.1.dist-info/METADATA
kpandas-0.0.1.dist-info/RECORD
